CHANGELOG.md
LICENSE
MANIFEST.in
README.md
requirements.txt
setup.cfg
setup.py
django_nomnom.egg-info/PKG-INFO
django_nomnom.egg-info/SOURCES.txt
django_nomnom.egg-info/dependency_links.txt
django_nomnom.egg-info/not-zip-safe
django_nomnom.egg-info/requires.txt
django_nomnom.egg-info/top_level.txt
docs/README.md
nomnom/__init__.py
nomnom/actions.py
nomnom/forms.py
nomnom/models.py
nomnom/settings.py
nomnom/urls.py
nomnom/utils.py
nomnom/views.py
nomnom/static/nomnom/img/tooltag-export.gif
nomnom/static/nomnom/img/tooltag-export_over.gif
nomnom/static/nomnom/img/tooltag-import.gif
nomnom/static/nomnom/img/tooltag-import_over.gif
nomnom/static/nomnom/img/tooltag-nomnom.gif
nomnom/static/nomnom/img/tooltag-nomnom_over.gif
nomnom/templates/.DS_Store
nomnom/templates/admin/change_list.html
nomnom/templates/admin/grappelli_change_list.html
nomnom/templates/nomnom/_object_tools_links.html
nomnom/templates/nomnom/nomnom_form.html
nomnom/tests/__init__.py
nomnom/tests/functional_tests.py
nomnom/tests/models.py
nomnom/tests/unit_tests.py