Metadata-Version: 1.0
Name: django-nomnom
Version: 0.1.4
Summary: Generic importing tool for the Django admin site.
Home-page: https://github.com/storyandstructure/django-nomnom/
Author: Kevin Harvey
Author-email: kevin@storyandstructure.com
License: MIT
Keywords: django,import,admin
Platform: OS Independent
Classifier: Development Status :: 3 - Alpha
Classifier: Environment :: Web Environment
Classifier: Framework :: Django
Classifier: Intended Audience :: Developers
Classifier: License :: OSI Approved :: MIT License
Classifier: Operating System :: OS Independent
Classifier: Programming Language :: Python
Classifier: Topic :: Internet :: WWW/HTTP :: Dynamic Content
Classifier: Topic :: Software Development
Classifier: Topic :: Software Development :: Libraries :: Application Frameworks
